MagicBaiduScholar/__init__.py
MagicBaiduScholar/config.py
MagicBaiduScholar/magic_baidu_scholar.py
MagicBaiduScholar/data/user_agents.txt
MagicBaiduScholar-0.0.1.dist-info/METADATA
MagicBaiduScholar-0.0.1.dist-info/RECORD
MagicBaiduScholar-0.0.1.dist-info/WHEEL
MagicBaiduScholar-0.0.1.dist-info/top_level.txt
