Metadata-Version: 2.1
Name: MagicBaiduScholar
Version: 0.0.1
Summary: A Baidu Scholar search results crawler
Home-page: https://github.com/1049451037/MagicBaiduScholar
Author: Qingsong Lv
Author-email: lqs@mail.bnu.edu.cn
License: UNKNOWN
Platform: UNKNOWN
Requires-Dist: beautifulsoup4
Requires-Dist: requests (>=2.12.4)
Requires-Dist: cchardet
